README.md
axians_netbox_pdu/__init__.py
axians_netbox_pdu/api/__init__.py
axians_netbox_pdu/api/serializers.py
axians_netbox_pdu/api/urls.py
axians_netbox_pdu/api/views.py
axians_netbox_pdu/choices.py
axians_netbox_pdu/filters.py
axians_netbox_pdu/forms.py
axians_netbox_pdu/management/__init__.py
axians_netbox_pdu/management/commands/__init__.py
axians_netbox_pdu/management/commands/pduscheduler.py
axians_netbox_pdu/migrations/0001_initial.py
axians_netbox_pdu/migrations/0002_pdustatus.py
axians_netbox_pdu/migrations/__init__.py
axians_netbox_pdu/models.py
axians_netbox_pdu/navigation.py
axians_netbox_pdu/tables.py
axians_netbox_pdu/template_content.py
axians_netbox_pdu/templates/axians_netbox_pdu/device_power_usage.html
axians_netbox_pdu/templates/axians_netbox_pdu/device_type_pduconfig.html
axians_netbox_pdu/templates/axians_netbox_pdu/pduconfig_edit.html
axians_netbox_pdu/templates/axians_netbox_pdu/pduconfig_list.html
axians_netbox_pdu/templates/axians_netbox_pdu/pduconfig_view.html
axians_netbox_pdu/templates/axians_netbox_pdu/rack_power_usage.html
axians_netbox_pdu/tests/__init__.py
axians_netbox_pdu/tests/test_pduconfig_api.py
axians_netbox_pdu/tests/test_pduconfig_views.py
axians_netbox_pdu/tests/test_pdustatus_api.py
axians_netbox_pdu/urls.py
axians_netbox_pdu/utilities.py
axians_netbox_pdu/views.py
axians_netbox_pdu/worker.py
axians_netbox_plugin_pdu-0.0.3.dist-info/WHEEL
axians_netbox_plugin_pdu-0.0.3.dist-info/METADATA
axians_netbox_plugin_pdu-0.0.3.dist-info/RECORD
