Metadata-Version: 2.1
Name: axians-netbox-plugin-pdu
Version: 0.0.3
Summary: A plugin for NetBox to easily display PDU information.
Home-page: https://github.com/minitriga/axians-netbox-plugin-pdu
License: Apache-2.0
Keywords: netbox,network,pdu,django,apc
Author: Alexander Gittings
Author-email: alexander.gittings@axians.co.uk
Requires-Python: >=3.6,<4.0
Classifier: License :: OSI Approved :: Apache Software License
Classifier: Programming Language :: Python :: 3
Classifier: Programming Language :: Python :: 3.6
Classifier: Programming Language :: Python :: 3.7
Classifier: Programming Language :: Python :: 3.8
Requires-Dist: easysnmp (>=0.2.5,<0.3.0)
Requires-Dist: invoke (>=1.4.1,<2.0.0)
Requires-Dist: rq-scheduler (>=0.10.0,<0.11.0)
Project-URL: Repository, https://github.com/minitriga/axians-netbox-plugin-pdu
